pyindexnum/__init__.py
pyindexnum/bilateral.py
pyindexnum/extension.py
pyindexnum/multilateral.py
pyindexnum/py.typed
pyindexnum/utils.py
pyindexnum-0.1.1.dist-info/METADATA
pyindexnum-0.1.1.dist-info/WHEEL
pyindexnum-0.1.1.dist-info/licenses/LICENSE
pyindexnum-0.1.1.dist-info/RECORD
