Metadata-Version: 2.4
Name: pyindexnum
Version: 0.1.1
Summary: Python library for index numbers calculations
License-File: LICENSE
Requires-Python: >=3.10
Requires-Dist: numpy<2.0.0,>=1.26.4
Requires-Dist: polars>=1.37.1
Requires-Dist: scipy>=1.11.0
